lspplot/__init__.py
lspplot/angular.py
lspplot/cmaps.py
lspplot/pc.py
lspplot/physics.py
lspplot/sclr.py
lspplot/untouched_colormaps.py
lspplot-0.1.7.data/scripts/EM.py
lspplot-0.1.7.data/scripts/angular.py
lspplot-0.1.7.data/scripts/angularmov.py
lspplot-0.1.7.data/scripts/energy_cons.py
lspplot-0.1.7.data/scripts/ion.py
lspplot-0.1.7.data/scripts/rho.py
lspplot-0.1.7.data/scripts/sclrq.py
lspplot-0.1.7.dist-info/METADATA
lspplot-0.1.7.dist-info/WHEEL
lspplot-0.1.7.dist-info/top_level.txt
lspplot-0.1.7.dist-info/RECORD
