Metadata-Version: 2.1
Name: lspplot
Version: 0.1.7
Summary: lsp plots
Home-page: http://github.com/noobermin/lspplot
Author: noobermin
Author-email: ngirmang.1@osu.com
License: MIT
Platform: UNKNOWN
Requires-Dist: pys (>=0.0.12r1)
Requires-Dist: lspreader (>=0.1.7)
Requires-Dist: matplotlib (>=3.0.0)
Requires-Dist: numpy (>=1.10.4)
Requires-Dist: scipy (>=0.18.1)
